{
    "traits": [
        "extroverted",
        "agreeable",
        "conscientious",
        "emotionally stable",
        "open"
    ],
    "attributes": [
        "adult",
        "male",
        "some schooling",
        "middle"
    ],
    "preferences": [
        "public transportation",
        "fast food",
        "ramen",
        "hobby shops",
        "university activities"
    ],
    "routines": [
        "commuting via train",
        "visiting parks",
        "attending university classes",
        "frequenting fast food restaurants",
        "exploring hobby shops"
    ],
    "user_profile": "User 1541 is a socially engaged adult male who enjoys exploring various places through public transportation, especially train stations, showing a preference for convenience and efficiency. He frequently visits fast food establishments and enjoys dining at ramen houses, indicating a preference for casual and quick dining options. His routine revolves around attending university, suggesting he values education and personal development. Additionally, he likes to explore hobby shops, reflecting a diverse range of interests. User 1541 is characterized by strong conscientiousness, often engaging in organized activities and maintaining a stable emotional state. He demonstrates a willingness to experience new things within familiar environments, suggesting high openness to new experiences. While regularly visiting places such as parks and educational institutions, he may also explore new locations in the future, such as additional fast-food outlets and local community centers."
}