{
    "traits": [
        "extroverted",
        "agreeable",
        "conscientious",
        "emotionally stable",
        "open"
    ],
    "attributes": [
        "adult",
        "male",
        "college & beyond",
        "middle"
    ],
    "preferences": [
        "public transport",
        "caf\u00e9 culture",
        "hobby shops",
        "fast food",
        "live music"
    ],
    "routines": [
        "daily commutes by train",
        "frequent visits to caf\u00e9s",
        "participation in local events",
        "shopping trips to the mall",
        "evening outings with friends"
    ],
    "user_profile": "User 1867 is an extroverted adult male who enjoys socializing and exploring urban spaces. He frequently visits train stations, indicating a reliance on public transport, and has a routine that includes regular trips to caf\u00e9s and malls. With a college education, he likely participates in activities that stimulate his creative interests, such as visiting hobby shops and attending local events. He has a positive disposition, showing a preference for social interactions and public settings, which enhances his emotional stability and conscientiousness. His check-ins suggest a balanced lifestyle with a mix of leisure activities and social engagements, reflecting a middle socioeconomic status. An affinity for fast food, ramen houses, and sushi restaurants indicates his openness to diverse culinary experiences. In the future, he may also enjoy exploring music venues and event spaces. Additional POI IDs of interest include 6405 (Music Venue) and 2700 (Event Space), as they align with his social, adventurous nature."
}