{
    "traits": [
        "extroverted",
        "agreeable",
        "conscientious",
        "emotionally stable",
        "open"
    ],
    "attributes": [
        "adult",
        "male",
        "college & beyond",
        "middle"
    ],
    "preferences": [
        "social gatherings",
        "exploring food options",
        "traveling"
    ],
    "routines": [
        "daily exercise",
        "morning commutes",
        "socializing during weekends"
    ],
    "user_profile": "User 6 is an outgoing and sociable male adult, likely in his late twenties or early thirties. He frequents train stations, suggesting he has a routine that involves travel, possibly for work or leisurely activities. With a healthy mix of conscientiousness and openness, he thrives in various social settings and enjoys exploring different cuisines, as evidenced by his visits to bars, cafes, and restaurants. This user displays a pattern of visiting train stations regularly, indicating a reliance on public transport. User 6 also frequents shopping malls which might suggest an interest in retail therapy or social outings with friends. He appears emotionally stable, handling stress well, and seems to prefer experiences that promote connection over isolation. His background indicates he possesses a solid educational foundation and is positioned within the middle socioeconomic level, suggesting a level of comfort that allows for exploration and enjoyment of diverse experiences. Key places of interest for the future could include an Indian restaurant (POI 2513) and a karaoke bar (suggested for social activities)."
}