{
    "traits": [
        "extroverted",
        "agreeable",
        "conscientious",
        "emotionally stable",
        "open"
    ],
    "attributes": [
        "adult",
        "male",
        "college & beyond",
        "middle"
    ],
    "preferences": [
        "travelling by train",
        "enjoying food & drink",
        "exploring new places"
    ],
    "routines": [
        "frequent visits to train stations",
        "regular dining at food shops",
        "occasional bus travel"
    ],
    "user_profile": "User 1448 is a socially active adult male who frequently travels, mainly using train services as evidenced by his regular check-ins at various train stations. His consistent visits to food and drink shops suggest a preference for exploring culinary options, adding enjoyment to his travel experiences. User 1448\u2019s routine reflects a well-organized schedule with significant engagement in social activities. He appears to be open to new experiences and enjoys discovering different places, as indicated by his diverse visits to numerous points of interest. He likely values connections and enjoys sharing experiences with others. This user's conscientiousness is shown through his organized travel patterns, moving from one station to another with purpose. Overall, User 1448 demonstrates a balance of sociability and emotional stability, likely making him a pleasant companion during his adventures. Notable future visits may include additional train stations and popular food spots, along with occasional exploration of stores and malls."
}