{
    "traits": [
        "introverted",
        "agreeable",
        "conscientious",
        "emotionally stable",
        "open"
    ],
    "attributes": [
        "adolescent",
        "male",
        "some schooling",
        "middle"
    ],
    "preferences": [
        "hobbies",
        "electronics",
        "Japanese cuisine",
        "Indian cuisine",
        "fast food",
        "arcades"
    ],
    "routines": [
        "visits hobby shops regularly",
        "frequently uses public transportation",
        "enjoys visiting restaurants",
        "spends time in parks and recreational spaces"
    ],
    "user_profile": "User 1139 is an adolescent male with a keen interest in hobbies, particularly in visiting various hobby shops. His check-ins reveal a pattern of frequent visits to electronic stores, emphasizing a preference for technology and gadgets. User 1139 enjoys diverse culinary experiences, evidenced by regular visits to Indian and Japanese restaurants, alongside conventional fast food establishments. He often utilizes public transportation, frequently checking in at train stations and subways, indicating a possibly mobile lifestyle that accommodates social interactions. Despite being generally introverted, this user exhibits agreeable traits by engaging in activities that allow him to connect with others, such as spending time in arcades and parks. His conscientious behavior is reflected in his structured routine of exploring interests, while his emotional stability suggests he is resilient and handles stress well. Overall, User 1139\u2019s profile points to an inquisitive individual eager to explore new experiences while balancing a love for technology and hobbies."
}