{
    "traits": [
        "extroverted",
        "agreeable",
        "conscientious",
        "emotionally stable",
        "open"
    ],
    "attributes": [
        "adult",
        "male",
        "college & beyond",
        "middle"
    ],
    "preferences": [
        "social gatherings",
        "reading",
        "trying new foods",
        "visiting parks"
    ],
    "routines": [
        "frequent bar visits",
        "visits to bookstores",
        "enjoying outdoor activities",
        "attending college events"
    ],
    "user_profile": "User 1547 is an adult male with a college education and a middle socioeconomic status. Characterized by extroversion, he enjoys socializing at bars and participating in various community events, evidencing a preference for social gatherings and group activities. He has a balanced approach to life, being emotionally stable and agreeable, which helps him navigate interactions positively. His conscientious nature suggests that he actively engages in routine activities including visiting bookstores, parks, and trying new foods, such as dumplings and BBQ. This user manifests openness to experiences, frequently exploring new dining options and attending events at college-related venues, which indicates a curious and exploratory mindset. Future predictions indicate a pattern that may include frequent visits to bars and parks, bookstores, and a curiosity for culinary experiences. Key points of interest may include local social hotspots (POI ID 2136), green spaces for relaxation (POI ID 2182), and venues that cater to his academic pursuits (POI ID 5695)."
}