{
    "traits": [
        "extroverted",
        "agreeable",
        "conscientious",
        "emotionally stable",
        "open"
    ],
    "attributes": [
        "adult",
        "male",
        "college & beyond",
        "middle"
    ],
    "preferences": [
        "socializing",
        "trying new restaurants",
        "visiting bars and cafes"
    ],
    "routines": [
        "commuting to work",
        "visiting coffee shops",
        "spending evenings at bars or restaurants"
    ],
    "user_profile": "User 214 is a sociable adult male with a penchant for exploring local bars, restaurants, and coffee shops. Having a background in higher education, he exhibits conscientious traits, demonstrating responsibility in his routines\u2014regularly visiting an office and train stations suggest a stable professional life. His sociable nature is evident from frequent visits to beer gardens and restaurants, indicating enjoyment in both social interactions and culinary experiences. User 214 likely enjoys meeting friends after work and unwinding at vibrant venues. His openness to experience is reflected in trying various types of cuisine, from Australian restaurants to burger joints. He is also emotionally stable, displaying resilience in his daily life. Key places of interest might include local bars (POI id 335), a nearby coffee shop (POI id 3333), and diverse eateries to explore for dining on weekends. Overall, User 214 blends a busy work life with active social engagements, showcasing a balanced lifestyle that prioritizes both career and leisure."
}