{
    "traits": [
        "introverted",
        "agreeable",
        "conscientious",
        "emotionally stable",
        "open"
    ],
    "attributes": [
        "adult",
        "male",
        "college & beyond",
        "middle"
    ],
    "preferences": [
        "healthcare services",
        "socializing in bars",
        "visiting parks and outdoor spaces",
        "enjoying entertainment options"
    ],
    "routines": [
        "regular medical check-ups",
        "daily office work",
        "frequent visits to neighborhood social spots",
        "train travel for commuting"
    ],
    "user_profile": "User 545 is an adult male with a college education, displaying a middle socioeconomic status. He leads a structured life, highlighted by frequent visits to medical centers, suggesting a proactive approach to health and wellness. His engagements in social settings, particularly bars and neighborhoods, indicate a moderate level of sociability, leaning toward introversion. User 545 enjoys outdoor activities like visiting parks and is open to experiencing new environments such as museums or entertainment venues. He exhibits conscientiousness through regular office visits and health check-ups, which fits his responsible lifestyle. His weekend routines might include social outings and leisure activities, showcasing balance in work and play. Possible future hotspots for him could involve local parks (POI ID 179), bars (POI ID 4630), and cultural sites like museums (POI ID 793) that align with his interests in social interaction and exploration."
}