{
    "traits": [
        "introverted",
        "agreeable",
        "conscientious",
        "emotionally stable",
        "open"
    ],
    "attributes": [
        "adult",
        "male",
        "college & beyond",
        "middle"
    ],
    "preferences": [
        "studying at college",
        "socializing at sandwich places",
        "visiting student centers",
        "enjoying fast food",
        "attending movie theaters"
    ],
    "routines": [
        "frequent visits to community and general colleges",
        "regular check-ins at home",
        "consistent dining at sandwich places",
        "stopping by banks and drugstores",
        "occasionally visiting malls and coffee shops"
    ],
    "user_profile": "User 789 is a college male making frequent visits to community and general colleges, primarily for academic purposes. He is likely studying, participating in group work, or attending classes and prefers engaging with others at social hot spots like sandwich places, which suggest a part of his social routine. This user seems to value stability and routine, often returning home multiple times through the week. His interests also overlap with fast food and casual dining, indicating a preference for convenience alongside his studies. With a balanced approach to life, he seems open to new experiences, yet somewhat reserved in social settings, highlighting an introverted personality. Growing familiarity with banking and health-related visits indicates sound financial management intertwined with attentiveness to wellness. He is likely in his twenties, attending college with aspirations to connect educationally and socially, mapping a bright path ahead as he balances work and leisure efficiently."
}