{
    "traits": [
        "extroverted",
        "agreeable",
        "conscientious",
        "emotionally stable",
        "open"
    ],
    "attributes": [
        "adult",
        "male",
        "college & beyond",
        "middle"
    ],
    "preferences": [
        "coffee shops",
        "gyms",
        "parks",
        "casual dining",
        "shopping"
    ],
    "routines": [
        "regular gym visits",
        "frequent coffee shop visits",
        "social outings in parks and neighborhoods",
        "shopping trips"
    ],
    "user_profile": "User 484 is an active adult male, likely in his late 20s to early 30s, who enjoys a balanced lifestyle that merges fitness and social interactions. He frequents coffee shops, such as POI 1563 and POI 1849, showcasing a penchant for casual atmospheres where he can relax or work. He exhibits high conscientiousness as reflected in his routine visits to gyms (POI 2747), demonstrating commitment to physical fitness. His social nature is evident through his visits to parks (POI 279, POI 1283) and BBQ joints (POI 759), indicating a preference for outdoor activities and communal dining experiences. User 484 displays an open personality, exploring various locations, including food shops and department stores (POI 858, POI 855). He maintains a middle socioeconomic status, indicated by his varied yet consistent spending habits. Future visits may include more parks and fitness-related locations, enhancing his active lifestyle."
}