{
    "traits": [
        "extroverted",
        "agreeable",
        "conscientious",
        "emotionally stable",
        "open"
    ],
    "attributes": [
        "adult",
        "male",
        "college & beyond",
        "middle"
    ],
    "preferences": [
        "bars",
        "restaurants",
        "theaters",
        "socializing",
        "exploring new cuisines"
    ],
    "routines": [
        "frequent visits to bars and restaurants",
        "regular social outings on weekends",
        "work routine at the office during weekdays"
    ],
    "user_profile": "User 1044 is an outgoing adult male in his late 20s, showcasing an extroverted personality through frequent visits to bars, restaurants, and theaters. He enjoys the atmosphere of social gatherings and often explores different cuisines, favoring Mexican, American, and diner-style food. His routine suggests a balance between work and leisure, with consistent check-ins at his office during weekdays followed by evenings spent dining out or at social venues. User 1044 appears emotionally stable with a knack for conscientiousness, indicating a reliable and dedicated approach to professional and personal commitments. He is open to new experiences, often indulging in a variety of culinary delights and various entertainment forms like theater and movies. Economically, he fits within the middle class, likely having completed college or higher education, which speaks to his stable social and financial background. Potential future check-in locations may include more diverse dining establishments, cultural events, or weekend getaways, reflecting his adventurous spirit."
}