{
    "traits": [
        "introverted",
        "agreeable",
        "conscientious",
        "emotionally stable",
        "open"
    ],
    "attributes": [
        "adult",
        "male",
        "college & beyond",
        "middle"
    ],
    "preferences": [
        "public transportation",
        "clothing shopping",
        "frequent visits to government offices",
        "deli food",
        "urban spaces"
    ],
    "routines": [
        "daily travels through bus and subway",
        "visiting government buildings regularly",
        "morning visits to delis for breakfast"
    ],
    "user_profile": "User 786 is a college-educated male in his 30s, characterized by an introverted yet agreeable personality. He appears conscientious and emotionally stable, with a propensity for new experiences. His frequent visits to government buildings suggest an engagement with civic duties, possibly related to work or personal interests in local governance. User 786\u2019s travel patterns indicate a reliance on public transportation, frequently utilizing the bus and subway systems, particularly to travel between home, work, and local facilities. He enjoys shopping at clothing stores, indicating a preference for maintaining a presentable appearance. Furthermore, regular stops at delis demonstrate a taste for convenient meal options, especially for breakfast. As a middle-class individual, he balances time between civic responsibilities and personal interests, making him likely to engage in social and recreational activities when not commuting. Future places of interest for User 786 might include additional government buildings (POI ID: 2751), clothing stores (POI ID: 1796), and local urban plazas (POI ID: 2604) that cater to his lifestyle."
}