{
    "traits": [
        "extroverted",
        "agreeable",
        "conscientious",
        "emotionally stable",
        "open"
    ],
    "attributes": [
        "adult",
        "male",
        "college & beyond",
        "middle"
    ],
    "preferences": [
        "traveling",
        "exploring new places",
        "socializing"
    ],
    "routines": [
        "frequent airport visits",
        "spending time at terminals",
        "planning trips"
    ],
    "user_profile": "User 1526 is a socially active adult male who enjoys traveling and exploring new destinations. His frequent visits to airports and terminals indicate a likely inclination towards travel, suggesting he may have either a job that requires regular flying or a strong personal passion for exploring new cultures. With a college education and middle socioeconomic status, he likely appreciates experiences that broaden his horizons, such as cultural events, local cuisines, and engaging in social activities. His behaviors indicate he is extroverted and agreeable, enjoying social interactions and forming connections. He appears to be conscientious, reflected in his organizational skills to manage ongoing travel schedules. Additionally, his emotional stability and openness to new experiences suggest he handles the uncertainties of travel well and embraces new challenges. In the future, he may visit various terminal locations (POIs) for both work and leisure, highlighting his adventurous spirit and sociable nature."
}