{
    "traits": [
        "extroverted",
        "agreeable",
        "conscientious",
        "emotionally stable",
        "open"
    ],
    "attributes": [
        "adult",
        "male",
        "college & beyond",
        "middle"
    ],
    "preferences": [
        "traveling",
        "motorsports",
        "spending time at resorts",
        "airport amenities",
        "social activities"
    ],
    "routines": [
        "frequent travel",
        "engaging in motorsport events",
        "relaxing at resorts",
        "possible involvement in community events"
    ],
    "user_profile": "User 3524 is an adult male with a penchant for travel and motorsport activities. He exhibits traits of an extrovert, showcasing a preference for social environments like airports and racetracks. His agreeable nature suggests he enjoys engaging with others and values social interactions. This user tends to plan and organize his trips, highlighting a conscientious streak. He appears emotionally stable, likely coping well with the stresses associated with travel. With a college education and a middle socioeconomic status, he has access to opportunities that facilitate his hobbies. Frequent visits to airports, whether for travel or leisure, indicate a robust interest in exploration and adventure. User 3524 also enjoys staying at resorts, which enhances his travel experiences. Future check-ins may include visits to notable destinations such as POI id 1113 (Airport), POI id 7711 (Racetrack), and POI id 8255 (Resort), indicating ongoing interests in travel and leisure activities that could shape his future routines."
}