{
    "traits": [
        "extroverted",
        "agreeable",
        "conscientious",
        "emotionally stable",
        "open"
    ],
    "attributes": [
        "adult",
        "male",
        "college & beyond",
        "upper"
    ],
    "preferences": [
        "business environments",
        "high-quality hotels",
        "Asian cuisine",
        "social dining experiences"
    ],
    "routines": [
        "frequent visits to corporate offices",
        "regular stays at modern hotels",
        "dining out at various restaurants"
    ],
    "user_profile": "User 2354 is a socially-active adult male who balances professional commitments with leisure activities. He frequently visits corporate offices, indicating a strong focus on work or business-related engagements. His preferences lean toward high-quality modern hotels, with several check-ins showcasing his routine of staying at these establishments, suggesting stability and comfort in his travel accommodations. User 2354 enjoys dining, with particular interest in Asian cuisine, often opting for social experiences in dining settings. This blend of interests points to an extroverted nature, enjoying interaction yet maintaining conscientious behavior through regular visits to established business locations. His educational background likely aligns with his adult status, suggesting he has completed college or higher education, and his upper socioeconomic status reflects in his frequent visits to upscale venues. As a generally emotionally stable individual, he navigates both work and social environments with ease, remaining open to new experiences, whether that be trying different cuisines or visiting various places."
}