{
    "traits": [
        "extroverted",
        "agreeable",
        "conscientious",
        "emotionally stable",
        "open to experience"
    ],
    "attributes": [
        "adult",
        "male",
        "college & beyond",
        "middle"
    ],
    "preferences": [
        "coffee shops",
        "American cuisine",
        "green spaces",
        "technological gadgets",
        "casual dining"
    ],
    "routines": [
        "frequent coffee shop visits",
        "shopping for groceries and tech",
        "dining out with friends"
    ],
    "user_profile": "User 931 is an adult male with a college education, belonging to the middle socioeconomic class. He demonstrates extroverted and agreeable traits, often socializing in various coffee shops, particularly at Starbucks and Peet's Coffee, indicating a strong preference for casual environments conducive to conversation and relaxation. He enjoys dining out in American, Mediterranean, and Asian restaurants, reflecting his diverse culinary interests. User 931 appears emotionally stable and conscientious, balancing leisure with responsibilities, as seen in his regular grocery shopping at Trader Joe's. His openness to experience is suggested by his visits to tech stores like Apple, highlighting an interest in new gadgets. This user enjoys routine social interactions and seeks comfort in familiar places, frequently returning to the same establishments, which could point to a preference for stability in his social life and relaxation habits."
}