{
    "traits": [
        "extroverted",
        "agreeable",
        "conscientious",
        "emotionally stable",
        "open"
    ],
    "attributes": [
        "adult",
        "male",
        "college & beyond",
        "middle"
    ],
    "preferences": [
        "social gatherings",
        "entertainment events",
        "casinos",
        "hotels",
        "varied dining"
    ],
    "routines": [
        "attending conventions",
        "participating in special events",
        "visiting casinos",
        "enjoying nightlife",
        "exploring new restaurants"
    ],
    "user_profile": "User 1543 is an outgoing male in his 30s, who enjoys a lively social life and actively participates in community events. With a background in higher education, he is likely to thrive in stimulating environments, often frequenting convention centers and special events. His love for entertainment is reflected in his numerous visits to casinos and various hotels, suggesting a preference for both leisure and engagement. User 1543 displays high levels of agreeableness and conscientiousness, indicating his reliability and friendliness in social settings. His routines revolve around attending events that foster social interaction, enabling him to connect with others and explore new experiences. Regular visits to sandwich shops and modern dining establishments further emphasize his appreciation for culinary diversity. He seems comfortable in bustling environments, which may lead him to continue exploring vibrant venues and community hotspots. Notable locations for future visits might include popular entertainment hubs, upscale dining options, and event-driven destinations."
}