{
    "traits": [
        "extroverted",
        "agreeable",
        "conscientious",
        "emotionally stable",
        "open"
    ],
    "attributes": [
        "adult",
        "female",
        "college & beyond",
        "middle"
    ],
    "preferences": [
        "travel",
        "exploring new cultures",
        "social gatherings",
        "community events",
        "food experiences"
    ],
    "routines": [
        "frequent travel",
        "visiting local markets",
        "dining at diverse cuisines",
        "attending sports events"
    ],
    "user_profile": "User 877 is an extroverted, socially engagin adult who's likely in her late twenties or early thirties, pursuing higher education and enjoying a middle socioeconomic status. Her frequent check-ins at various airports indicate a love for travel and adventure, suggesting she enjoys exploring new places and cultures. User 877's visits to a stadium and corporate office show that she is not only interested in sports but may also be engaged in a professional lifestyle, reflecting her conscientious nature. The variety in her dining experiences\u2014from African to Mexican cuisines\u2014demonstrates her openness to new experiences and flavors. This user regularly visits local eateries and markets, indicating a strong preference for community engagement and culinary adventures. With an emotionally stable disposition, she blends social interactions with work and leisure, likely leading a busy yet balanced life. Moving forward, potential places of interest could include additional local markets, diverse restaurants, and sports venues, affirming her lifestyle as a food enthusiast and an active community participant."
}