{
    "traits": [
        "extroverted",
        "agreeable",
        "conscientious",
        "emotionally stable",
        "open"
    ],
    "attributes": [
        "adult",
        "male",
        "college & beyond",
        "middle"
    ],
    "preferences": [
        "nightlife",
        "diverse cuisines",
        "art and culture",
        "travel",
        "entertainment"
    ],
    "routines": [
        "visiting bars and lounges",
        "attending galleries and theaters",
        "exploring new restaurants",
        "frequent travel"
    ],
    "user_profile": "User 1417 is an adventurous 30-year-old male who thrives on social interactions and cultural experiences. He frequents dive bars, ultra-lounges, and diverse restaurants, exhibiting an open and extroverted personality. A college graduate with a stable middle-income lifestyle, he enjoys nightlife and culinary variety, often found exploring new cuisines like Asian, Italian, and South American. User 1417 is emotionally stable, appearing to enjoy social gatherings and events, which indicates a high level of agreeableness in his interactions. His diverse check-ins reveal a passion for art and history, as seen in his frequent visits to galleries and theaters, alongside an interest in exploring landmarks and museums. Notably, he has a recurring pattern of visiting airports, indicating a love for travel, likely including weekend getaways or trips to theme parks, further stressing his extroverted nature. As he continues to frequent vibrant locales, including historic sites and modern amenities, he remains open to experiences that enrich his social life."
}