{
    "traits": [
        "extroverted",
        "agreeable",
        "conscientious",
        "neurotic",
        "open"
    ],
    "attributes": [
        "adult",
        "male",
        "college & beyond",
        "middle"
    ],
    "preferences": [
        "coffee shops",
        "Asian cuisine",
        "casinos",
        "malls",
        "travel"
    ],
    "routines": [
        "frequent airport visits",
        "regular coffee shop check-ins",
        "mall visits",
        "dining out",
        "engaging in leisure activities"
    ],
    "user_profile": "User 234 is an extroverted male in his late 30s to early 40s, with a college education and a middle socioeconomic status. He frequently visits places like airports (POI ID: 562), Starbucks (POI ID: 5237), and various malls (POI ID: 1147, 3451). His routine suggests that he enjoys dining out, especially Asian cuisine (POI ID: 8104), and has a penchant for visiting casinos (POI IDs: 5619, 564, 945). User 234's lifestyle reflects a preference for social interactions and leisure activities, often engaging in shopping and dining experiences. He is open to new experiences and enjoys traveling, as indicated by his multiple airport check-ins. User 234's regular visits to coffee shops and malls show a balance between social enjoyment and everyday routines, suggesting he values both relaxation and exploration."
}