{
    "traits": [
        "extroverted",
        "agreeable",
        "conscientious",
        "emotionally stable",
        "open"
    ],
    "attributes": [
        "adult",
        "male",
        "college & beyond",
        "middle"
    ],
    "preferences": [
        "Coffee Shops",
        "American Cuisine",
        "Health & Fitness",
        "Dine-out",
        "Grocery Shopping",
        "Cultural Events"
    ],
    "routines": [
        "Daily caf\u00e9 visits",
        "Frequent grocery shopping",
        "Regular fitness activities",
        "Weekend outings",
        "Multiple visits to the same venues"
    ],
    "user_profile": "User 1206, a middle-income male in his late twenties, has shown a consistent pattern of engaging in social and culinary experiences. His frequent visits to various coffee shops, including Peet's Coffee and Trader Joe's, indicate a preference for community spaces and healthy eating. User 1206 tends to visit his apartment frequently, suggesting it serves as a base for his lifestyle. He favors a range of dining experiences, with American, Italian, and French cuisines capturing his interest. With a focus on health and fitness, regular visits to gyms and health stores highlight a conscientious approach to wellness. The user\u2019s routine reveals an affinity for social outings, particularly at dive bars and cultural events, indicating an extroverted personality. The frequent visits to the Warehouse & Industrial POI suggest a professional or recreational interest in these types of venues. Engagement with community activities and cultural explorations hints at openness to new experiences. User 1206\u2019s profile reflects a blend of a healthy lifestyle, social engagement, and culinary adventures, likely leading to future visits to popular eateries and community-centric events."
}