{
    "traits": [
        "extroverted",
        "agreeable",
        "conscientious",
        "emotionally stable",
        "open"
    ],
    "attributes": [
        "adult",
        "male",
        "college & beyond",
        "upper"
    ],
    "preferences": [
        "Italian cuisine",
        "Mediterranean food",
        "casual dining",
        "entertainment activities",
        "luxury experiences"
    ],
    "routines": [
        "frequent travels",
        "dining out and trying different cuisines",
        "attending entertainment events",
        "visiting malls and shopping",
        "exploring cultural experiences"
    ],
    "user_profile": "User 668 is an outgoing and adventurous male in his 30s who enjoys a rich variety of dining experiences and entertainment. With a college degree, he operates within an upper socioeconomic bracket. He frequently visits airports, indicating a love for travel, and enjoys meals at diverse restaurants, often choosing Italian and Mediterranean cuisines. His check-ins also show a penchant for casual fast food options like burgers, as well as indulgences at luxury hotels and theaters. Regular visits to casinos and malls suggest a playful, social lifestyle and a preference for entertainment. His consistency in visiting cineplexes, pubs, and diners points to an appreciation for leisure activities. User 668 is open to new experiences, valuing both social interactions and cultural enrichment, promising a future filled with exciting adventures at similar venues including airports, malls (POI ids 321, 1706), and various entertainment centers (POI ids 2020, 2054)."
}