{
    "traits": [
        "extroverted",
        "agreeable",
        "conscientious",
        "emotionally stable",
        "open"
    ],
    "attributes": [
        "adult",
        "female",
        "college & beyond",
        "middle"
    ],
    "preferences": [
        "technology",
        "outdoor activities",
        "fast food",
        "shopping",
        "social gatherings"
    ],
    "routines": [
        "visiting parks regularly",
        "frequenting technology stores",
        "dining out on the weekends",
        "shopping for groceries every week"
    ],
    "user_profile": "User 3808 is an extroverted and agreeable adult female with a college background. She enjoys a balanced lifestyle, combining her interests in technology and the outdoors. Her visits to the city park and technology-related locations indicate a preference for outdoor activities and tech innovations. She loves dining out, particularly at fast-food places like In-N-Out Burger and local burger joints, indicating some indulgence in comfort food. User 3808 also demonstrates conscientious behavior, as seen in her routine of grocery shopping at Trader Joe's and her engagement with community places like City Hall. Her willingness to explore different cuisines suggests she is open to new experiences. This user is likely to continue visiting parks and technology stores, and future check-ins may include visits to community events, museums, and health-oriented cafes or shops."
}