{
    "traits": [
        "extroverted",
        "agreeable",
        "conscientious",
        "emotionally stable",
        "open"
    ],
    "attributes": [
        "adult",
        "male",
        "college & beyond",
        "upper"
    ],
    "preferences": [
        "casinos",
        "Mexican cuisine",
        "performing arts",
        "theatre",
        "light rail transportation"
    ],
    "routines": [
        "frequent visits to casinos",
        "enjoying varied cuisine",
        "attending theatrical performances",
        "engaging in social activities"
    ],
    "user_profile": "User 2822 is an extroverted adult male in his early thirties, actively engaged in the vibrant social scene of entertainment and dining. He often visits casinos, indicating a preference for upbeat and dynamic experiences. His affinity for diverse cuisines, especially Mexican and Asian food, suggests a developed palate and openness to new culinary adventures. User 2822 enjoys the performing arts, frequently attending theatre productions, which showcases his appreciation for cultural experiences. With an academic background that likely extends to college or beyond, he balances a busy lifestyle filled with leisure and social interactions. His routine includes frequent travels, often revolving around airports, hinting at a lifestyle rich in movement and exploration. He favors higher socioeconomic environments, as indicated by his choice of luxury hotels during his excursions. In the future, he may continue to explore places related to entertainment, gastronomy, and culture, particularly with a focus on casinos and theatrical venues, such as POIs 945 (Casino), 6492 (Theatre), and 5311 (Asian Food)."
}