{
    "traits": [
        "extroverted",
        "agreeable",
        "conscientious",
        "emotionally stable",
        "open"
    ],
    "attributes": [
        "adult",
        "male",
        "college & beyond",
        "middle"
    ],
    "preferences": [
        "art",
        "Asian cuisine",
        "social gatherings",
        "science",
        "baking",
        "reading",
        "French cuisine"
    ],
    "routines": [
        "visiting museums",
        "dining out",
        "attending social events",
        "exploring bookstores",
        "enjoying desserts"
    ],
    "user_profile": "User 543 is an extroverted adult male in his late 20s with a college education and a middle socioeconomic status. He has a diverse range of interests, reflected in his frequent visits to modern art and science museums, Asian and French restaurants, and a popular local bakery. His love for culture fuels his exploration of both art and cuisine, showcasing an open-minded approach to experiences. User 543 shows a consistent pattern of visiting social venues, like pubs, indicating a strong inclination towards social interaction. His affinity for reading at bookstores suggests a contemplative side, balancing his sociable nature. He values cultural experiences, often frequenting places that mention art and science. Future check-ins might include visits to specific locations like the City Art Gallery (POI ID 1122) or the Local Music Festival (POI ID 5732), enhancing his practices in leisure and social engagement."
}