{
    "traits": [
        "extraverted",
        "agreeable",
        "conscientious",
        "emotionally stable",
        "open"
    ],
    "attributes": [
        "adult",
        "male",
        "college & beyond",
        "middle"
    ],
    "preferences": [
        "traveling",
        "gambling",
        "luxury experiences",
        "urban exploration",
        "casual socializing"
    ],
    "routines": [
        "frequent travel",
        "night outings",
        "social events",
        "visiting entertainment venues",
        "exploring new cities"
    ],
    "user_profile": "User 3302, a male in his late 20s, is an adventurous individual who enjoys exploring new experiences and social settings. He is likely a college-educated professional who finds joy in traveling, often visiting airports, luxury hotels, and casinos. His check-ins indicate a penchant for nightlife, as evidenced by multiple casino visits and late-night outings to entertainment venues. User 3302 possesses a warm and friendly demeanor, indicating a high level of agreeableness, and is likely emotionally stable, comfortably engaging in social situations without excessive anxiety. His inclination toward exploring urban areas shows openness to experience, while his structure in routines and planning suggests a conscientious side. Future places of interest for User 3302 could include other high-end casinos, famous tourist attractions, and vibrant nightlife areas that encourage social interactions and entertainment."
}