{
    "traits": [
        "extroverted",
        "agreeable",
        "conscientious",
        "emotionally stable",
        "open"
    ],
    "attributes": [
        "adult",
        "female",
        "college & beyond",
        "middle"
    ],
    "preferences": [
        "coffee",
        "casual dining",
        "academic environments",
        "French cuisine"
    ],
    "routines": [
        "visits coffee shops regularly",
        "attends university classes",
        "enjoys dining out with friends"
    ],
    "user_profile": "User 2028 is an extroverted and agreeable individual in their late 20s, currently pursuing a college degree. They frequent Starbucks, suggesting a love for coffee and social settings, and enjoy casual dining at burgers and French restaurants, indicating a preference for diverse culinary experiences. Their check-ins at the university reveal a commitment to their academic growth and a structured routine that balances study and social life. User 2028 demonstrates conscientiousness through their consistent university attendance, reflecting a goal-oriented mindset. With a balanced emotional state, they navigate challenges effectively, likely contributing to a robust social circle. Open to new experiences, they exhibit curiosity about different cuisines and lively atmospheres. Future visits may include exploring new coffee shops or restaurants (POI ids: 2547, 5728, 675, 3665), as well as the potential for further academic opportunities (POI id 3569). Their middle socioeconomic status affords them the ability to indulge in dining and social outings. Overall, User 2028 embodies a vibrant, community-oriented lifestyle enriched by educational pursuits and culinary adventures."
}