{
    "traits": [
        "introverted",
        "agreeable",
        "conscientious",
        "emotionally stable",
        "open"
    ],
    "attributes": [
        "adult",
        "female",
        "college & beyond",
        "middle"
    ],
    "preferences": [
        "reading",
        "Asian cuisine",
        "grocery shopping",
        "visiting bookstores",
        "traveling"
    ],
    "routines": [
        "visiting bookstores regularly",
        "frequently dining at Asian restaurants",
        "making routine bank visits",
        "grocery shopping every month",
        "traveling occasionally"
    ],
    "user_profile": "User 3854 is a college-educated adult female with a strong interest in literature and culture, often visiting bookstores to discover new reads. She enjoys dining at Asian restaurants, reflecting her appreciation for diverse cuisines. Her routine includes regular trips to the grocery store and banking establishments, indicating a conscientious nature. User 3854 leads a balanced life, often utilizing public transport, as highlighted by her frequent visits to train stations and airports. She values organization and planning, suggesting a reliable daily schedule that supports her academic or professional life, likely tied to her university background. This user showcases a blend of introverted qualities, often preferring low-key activities over large social gatherings, yet remains open to new experiences. She is expected to visit locations such as the local university, corporate offices, and cultural events in the future, maintaining an overall stable lifestyle."
}