{
    "traits": [
        "introverted",
        "agreeable",
        "conscientious",
        "emotionally stable",
        "open"
    ],
    "attributes": [
        "adolescent",
        "female",
        "some schooling",
        "middle"
    ],
    "preferences": [
        "fast food",
        "healthy snacks",
        "hygiene products"
    ],
    "routines": [
        "visiting 24 Hour Fitness regularly",
        "frequenting Subway for meals",
        "enjoying frozen treats"
    ],
    "user_profile": "User 3735 is an adolescent female with a penchant for casual dining spots, particularly fast food and healthy snacks. Her frequent visits to In-N-Out Burger and Subway suggest she values convenience and enjoys recognizable food chains. The pattern of selecting frozen yogurt and ice cream places indicates a sweet tooth, hinting at openness to enjoyment and exploration in her culinary choices. Regular check-ins at 24 Hour Fitness highlight her commitment to fitness and healthy living, suggesting a conscientious nature. Given her routine preferences, she might lean towards social outings that are aligned with food and fitness, reflecting agreeable traits in planning social activities. The balance between social environments and solitary settings reveals a predominantly introverted personality that still enjoys engaging experiences. In the future, she may visit other active spaces like parks or recreational centers (suggested POI IDs could include local parks or yoga studios). As she continues to explore and express herself through culinary experiences, her lifestyle is characterized by a healthy balance between indulging in favorite foods and maintaining fitness commitments."
}