{
    "traits": [
        "extroverted",
        "agreeable",
        "conscientious",
        "emotionally stable",
        "open"
    ],
    "attributes": [
        "adult",
        "male",
        "college & beyond",
        "upper"
    ],
    "preferences": [
        "Mediterranean cuisine",
        "luxury experiences",
        "cultural arts",
        "entertainment at casinos",
        "nightlife",
        "traveling"
    ],
    "routines": [
        "socializing on weekends",
        "dining at upscale restaurants",
        "visiting cultural sites",
        "frequent casino visits",
        "engaging in nightlife activities"
    ],
    "user_profile": "User 1503 is an extroverted adult male who enjoys exploring upscale dining and entertainment options. With a preference for Mediterranean and American cuisines, he often visits luxury venues and indulges in cultural experiences, such as performing arts and museums. His frequent check-ins at various casinos suggest a love for games of chance and nightlife, indicative of a dynamic social life. User 1503 tends to socialize in lively environments, such as ultra-lounges and dancefloors, where he connects with others in a vibrant setting. He also enjoys leisure activities at gardens, which indicates a balance between high-energy events and relaxation. With a college education and an upper socioeconomic status, he gravitates toward enriched life experiences and values cultural engagement. Notably, his patterns suggest a penchant for travel, luxury hotels, and artisan foods. Future check-in locations may include POI IDs like 5044 (Mediterranean), 328 (Luxury Hotel), and 328 (Casino), continuing to reflect his diverse and sophisticated lifestyle."
}