{
    "traits": [
        "extroverted",
        "agreeable",
        "conscientious",
        "emotionally stable",
        "open"
    ],
    "attributes": [
        "adult",
        "male",
        "college & beyond",
        "middle"
    ],
    "preferences": [
        "coffee shops",
        "live music",
        "sushi",
        "technology",
        "casual dining",
        "art and culture"
    ],
    "routines": [
        "visiting cafes in the morning",
        "attending live music events on weekends",
        "exploring different cuisines during the week"
    ],
    "user_profile": "User 3273 is an adult male who enjoys a vibrant social life filled with diverse culinary experiences and cultural activities. He frequents coffee shops such as Peet's and Starbucks, indicating his love for caffeine-fueled social gatherings or study sessions. His taste in food is varied, as he often visits sushi bars, diners, and BBQ joints, suggesting he appreciates both casual dining and adventurous flavors. This user demonstrates extroverted qualities, enjoying the company of others and participating in live music events, possibly reflecting his openness to new experiences. His visits to places like art museums and historic landmarks indicate a curiosity about culture and history, while his regular appearances at tech-related venues suggest a conscientious side that values learning and skill development. With a college background and a middle socioeconomic status, user 3273 balances leisure with a sense of purpose in his daily routines, likely exploring new and exciting places while maintaining a steady social life. Future check-in possibilities include popular events, tech fairs, and new cafes in the area, enhancing his quest for enjoyable experiences."
}