{
    "traits": [
        "extroverted",
        "agreeable",
        "conscientious",
        "emotionally stable",
        "open"
    ],
    "attributes": [
        "adult",
        "male",
        "college & beyond",
        "middle"
    ],
    "preferences": [
        "coffee shops",
        "casual dining",
        "exploring new eateries",
        "bookstores",
        "technology"
    ],
    "routines": [
        "frequent visits to coffee shops",
        "dining at fast-casual restaurants",
        "engaging in social outings",
        "browsing bookstores",
        "trips to tech stores"
    ],
    "user_profile": "User 185 is a socially active male adult who enjoys exploring a variety of dining options, including coffee shops, fast-casual eateries, and bookstores. He often visits popular places like Starbucks and Five Guys, indicating a preference for relaxed environments where he can socialize or work. His routine includes frequent check-ins at corporate offices and tech-related venues like Apple and Best Buy, suggesting a professional and possibly tech-savvy background. User 185 is likely in the middle socioeconomic class and has completed higher education. His visits to places like luxury hotels and airports may hint at an openness to travel and experiencing diverse cultures. Overall, his extroverted nature fosters a love for social interactions while maintaining a stable emotional state. Important places User 185 may visit in the future might include popular cafes, tech stores, and cultural sites. His dynamic and exploratory lifestyle paints the portrait of an adventurous individual who embraces new experiences while staying grounded in familiar comforts."
}