{
    "traits": [
        "extroverted",
        "agreeable",
        "conscientious",
        "emotionally stable",
        "open"
    ],
    "attributes": [
        "adult",
        "male",
        "college & beyond",
        "middle"
    ],
    "preferences": [
        "music",
        "socializing",
        "going to bars",
        "eating out",
        "live performances",
        "varied cuisine"
    ],
    "routines": [
        "frequent visits to bars",
        "attending concerts and music events",
        "watching movies",
        "social gatherings",
        "exploring new restaurants"
    ],
    "user_profile": "User 146 is an active adult male in his late 20s, pursuing or recently completed a college education. He enjoys socializing, as evident from his frequent visits to bars, music venues, and concerts, reflecting a strong extroverted personality. He appreciates diverse culinary experiences, often dining out at various restaurants, such as pizza places and Asian cuisine locales. His routine includes regular attendance at local music performances and movie theaters, indicating a preference for entertainment and culture. User 146 has a generally positive demeanor and seeks engaging social experiences, suggesting high agreeableness and emotional stability. He also displays conscientiousness in maintaining a balanced social life alongside his professional commitments, as indicated by his visits to an office setting. His openness to experiences allows for exploration of new activities, whether it's trying out different food locations or attending various live performances. Important places he may visit in the future include additional bars, music venues, and food spots (POI IDs: 250, 562, 286). Overall, User 146\u2019s profile suggests someone who thrives in social situations and is eager to experience what the local culture has to offer."
}