{
    "traits": [
        "extroverted",
        "agreeable",
        "conscientious",
        "emotionally stable",
        "open to experience"
    ],
    "attributes": [
        "adult",
        "female",
        "college & beyond",
        "middle"
    ],
    "preferences": [
        "outdoor activities",
        "socializing in neighborhoods",
        "visiting diners and pizza places",
        "visiting parks frequently",
        "traveling via public transport"
    ],
    "routines": [
        "regular visits to parks and outdoor areas",
        "consistent check-ins at local diners and pizza places",
        "frequent trips to the neighborhood",
        "visits to airports and stations indicating travel"
    ],
    "user_profile": "User 192 is an active adult female who enjoys spending time in local neighborhoods and parks. With an outgoing personality, she exhibits extroverted traits, frequently socializing in community areas. Her routine includes regular visits to diners, pizza venues, and engaging outdoor locations, suggesting a strong preference for both socializing and experiencing nature. Educationally, she is well-educated, having completed college, which complements her conscientious and open to experience personality. Financially, she enjoys a comfortable middle-class lifestyle, allowing for exploration and leisure activities. User 192 shows a tendency to travel, frequently visiting airports and various public transport hubs, indicating an adventurous spirit. Essential places of interest in her future predictions include POI IDs 2942 (Neighborhood), 752 (Diner), 380 (Park) and 4570 (Other Great Outdoors), as her patterns suggest a continued affinity for engaging in community engagements and nature explorations."
}