{
    "traits": [
        "extroverted",
        "agreeable",
        "conscientious",
        "emotionally stable",
        "open"
    ],
    "attributes": [
        "adult",
        "male",
        "college & beyond",
        "middle"
    ],
    "preferences": [
        "frequent train travel",
        "visits to cafes",
        "interest in electronics",
        "engagement in university life"
    ],
    "routines": [
        "daily commutes via train",
        "regular visits to university",
        "frequent caf\u00e9 excursions",
        "shopping for electronics"
    ],
    "user_profile": "User 620 is an energetic and sociable male adult who often engages in activities reflecting his conscientious nature. A college student, he demonstrates a strong commitment to academics, frequently visiting his university. His routine is heavily focused on commuting, particularly by train, indicating a preference for structured travel. This user shows a keen interest in electronics and enjoys relaxing at local cafes. His agreeable personality allows him to thrive in social settings, making friends along the way. Frequent interactions at university events and social hotspots suggest he values connections with others. In addition, he often indulges in dining experiences, particularly at Japanese restaurants. User 620 is open to new experiences, which plays a vital role in his lifestyle. Noteworthy locations include various train stations, electronics stores, and cafes where he might continue exploring in the future. He likely falls within the middle socioeconomic level, balancing academic pursuits and leisure activities with a well-rounded lifestyle."
}