{
    "traits": [
        "introverted",
        "agreeable",
        "conscientious",
        "emotionally stable",
        "open to experience"
    ],
    "attributes": [
        "adult",
        "male",
        "college & beyond",
        "middle"
    ],
    "preferences": [
        "Ramen",
        "Gym/Fitness Center",
        "Office environment",
        "Movies",
        "Travel"
    ],
    "routines": [
        "Commutes regularly, likely for work",
        "Frequent gym visits",
        "Dining out, especially at Ramen or Noodle houses",
        "Occasional spa or massage visits",
        "Enjoys visiting various train stations"
    ],
    "user_profile": "User 852 is an adult male with a preference for structured environments, evident from frequent visits to an office setting (POI ID 7075). This indicates a conscientious nature, likely engaging in professional activities. The user shows a tendency towards introversion, preferring smaller, intimate dining experiences at Ramen and Noodle houses (POI ID 2183), reflecting comfort in low-pressure social settings. Fitness is important, as seen through regular check-ins at a gym (POI ID 2225), suggesting a commitment to health. Their routine is marked by frequent commutes to train stations (various POI IDs) suggesting travel for work or leisure. They display emotional stability as they engage in various recreational activities, such as visiting movie theaters (POI ID 2052) and spas (POI ID 6168), showcasing an interest in relaxation and entertainment. With an inclination for exploring diverse culinary options, they have a moderate openness to experience, contributing to a dynamic but balanced lifestyle. Expect future check-ins to include favorite places mentioned and a mix of social and solo activities."
}