{
    "traits": [
        "Introverted",
        "Agreeable",
        "Conscientious",
        "Emotionally Stable",
        "Open"
    ],
    "attributes": [
        "Adult",
        "Male",
        "College & Beyond",
        "Middle"
    ],
    "preferences": [
        "hobbies",
        "reading",
        "art galleries",
        "caf\u00e9s",
        "hobby shops"
    ],
    "routines": [
        "visiting bookstores",
        "frequenting train stations and subways",
        "attending events at convention centers",
        "exploring parks and art galleries"
    ],
    "user_profile": "User 1026 is an adult male with a penchant for quiet activities, suggesting an introverted nature. He enjoys spending time at hobby shops and bookstores, reveling in interests like reading and artistic pursuits. His consistent visits to various train stations and subways reflect a structured lifestyle, potentially indicative of a conscientious personality. While he appears to appreciate social environments, such as caf\u00e9s and convention centers, he displays emotional stability, suggesting he is comfortable in his routines. He is open to new experiences, frequently exploring art galleries and attending events. This user likely values creativity and learning, as seen in his choice of hobbies and interests. Future check-ins could include plans for visiting local art exhibits or book fair events, as well as ongoing explorations of parks and galleries. Key POI IDs that could guide predictions in the future include POI ID 2095 (Hobby Shop), POI ID 4210 (Bookstore), POI ID 6389 (Art Gallery), and POI ID 4506 (Caf\u00e9)."
}